{
    "Ib": [
        1.331, 
        3.107, 
        4.216, 
        4.956, 
        5.252, 
        7.25, 
        7.546, 
        9.987, 
        9.247, 
        12.724, 
        12.872, 
        16.054, 
        15.98, 
        18.421, 
        18.569, 
        23.526, 
        21.084, 
        25.301, 
        25.153, 
        26.115, 
        29.962, 
        30.776, 
        33.513, 
        31.294, 
        36.399, 
        37.212, 
        40.246, 
        39.95, 
        45.868, 
        45.868, 
        44.019, 
        48.828, 
        49.419, 
        51.491, 
        53.488, 
        55.856, 
        57.484, 
        58.371, 
        59.259, 
        62.292, 
        65.917, 
        66.287, 
        69.543, 
        71.614, 
        74.943, 
        73.02, 
        76.719, 
        76.497, 
        79.234, 
        81.306, 
        82.933, 
        83.673, 
        87.52, 
        89.962, 
        91.145, 
        90.849, 
        94.253, 
        98.839, 
        97.36, 
        97.434, 
        103.13, 
        104.092, 
        104.018, 
        108.827, 
        110.307, 
        110.381, 
        111.194, 
        116.003, 
        116.965
    ], 
    "Ic": [
        1.058, 
        1.508, 
        1.784, 
        2.364, 
        2.756, 
        3.017, 
        3.916, 
        4.119, 
        5.251, 
        5.251, 
        6.121, 
        6.672, 
        8.007, 
        8.196, 
        9.4, 
        9.472, 
        10.488, 
        11.445, 
        11.837, 
        13.113, 
        13.36, 
        14.854, 
        14.883, 
        16.45, 
        16.812, 
        18.074, 
        18.19, 
        19.597, 
        20.323, 
        20.482, 
        21.715, 
        22.368, 
        22.977, 
        24.37, 
        25.24, 
        25.661, 
        26.604, 
        27.286, 
        28.2, 
        29.201, 
        29.389, 
        30.825, 
        31.014, 
        32.073, 
        32.334, 
        33.422, 
        34.278, 
        34.728, 
        36.077, 
        36.686, 
        37.571, 
        38.006, 
        38.731, 
        39.181, 
        40.051, 
        40.617, 
        41.908, 
        42.256, 
        42.503, 
        43.721, 
        44.505, 
        44.519, 
        44.519, 
        44.519, 
        44.519, 
        44.519, 
        44.519, 
        44.519, 
        44.519
    ], 
    "Rb": 338, 
    "Vb": [
        0.618, 
        0.623, 
        0.631, 
        0.634, 
        0.642, 
        0.644, 
        0.649, 
        0.652, 
        0.651, 
        0.659, 
        0.659, 
        0.664, 
        0.664, 
        0.667, 
        0.665, 
        0.668, 
        0.668, 
        0.668, 
        0.673, 
        0.673, 
        0.673, 
        0.673, 
        0.675, 
        0.675, 
        0.677, 
        0.678, 
        0.678, 
        0.678, 
        0.678, 
        0.678, 
        0.678, 
        0.678, 
        0.68, 
        0.68, 
        0.678, 
        0.683, 
        0.68, 
        0.681, 
        0.68, 
        0.68, 
        0.683, 
        0.683, 
        0.683, 
        0.683, 
        0.683, 
        0.681, 
        0.683, 
        0.683, 
        0.683, 
        0.685, 
        0.683, 
        0.683, 
        0.683, 
        0.683, 
        0.683, 
        0.683, 
        0.683, 
        0.683, 
        0.681, 
        0.683, 
        0.683, 
        0.683, 
        0.683, 
        0.683, 
        0.683, 
        0.683, 
        0.683, 
        0.683, 
        0.683
    ], 
    "Vb0": 654, 
    "hFE": 459
}